__init__.py
autora/__init__.py
autora/theorist/__init__.py
autora/theorist/toolkit/__init__.py
autora/theorist/toolkit/utils.py
autora/theorist/toolkit/components/__init__.py
autora/theorist/toolkit/components/nodes.py
autora/theorist/toolkit/components/primitives.py
autora/theorist/toolkit/methods/__init__.py
autora/theorist/toolkit/methods/fitting.py
autora/theorist/toolkit/methods/metrics.py
autora/theorist/toolkit/methods/regression.py
autora/theorist/toolkit/methods/rules.py
autora/theorist/toolkit/models/__init__.py
autora/theorist/toolkit/models/bayesian_machine_scientist.py
autora/theorist/toolkit/models/bayesian_symbolic_regression.py
autora/theorist/toolkit/models/ddm_bms.py
autora/theorist/toolkit/models/hierarchical_bayesian_symbolic_regression.py
autora/theorist/toolkit/models/hierarchical_symbolic_regressor.py
autora/theorist/toolkit/models/hybrid_regression.py
autora/theorist/toolkit/models/memory.py
autora/theorist/toolkit/models/parallel_symbolic_regression.py
autora/theorist/toolkit/models/symbolic_regression.py
autora/theorist/toolkit/models/tree.py
autora_theorist_toolkit-0.3.0.dist-info/METADATA
autora_theorist_toolkit-0.3.0.dist-info/WHEEL
autora_theorist_toolkit-0.3.0.dist-info/top_level.txt
autora_theorist_toolkit-0.3.0.dist-info/RECORD
