Metadata-Version: 2.1
Name: autora-theorist-toolkit
Version: 0.3.0
Summary: Toolkit to build algorithms for model recovery
Author-email: "Joshua T. S. Hewson" <joshua_hewson@brown.edu>
License: MIT license
Project-URL: homepage, http://www.empiricalresearch.ai
Project-URL: repository, https://github.com/TheLemonPig/autora-theorist-toolkit
Project-URL: documentation, https://autoresearch.github.io/autora/
Requires-Python: <4,>=3.8
Requires-Dist: autora-core
Requires-Dist: scikit-learn
Requires-Dist: numpy
Requires-Dist: scipy
Requires-Dist: tqdm
Requires-Dist: pandas
Requires-Dist: sympy
Provides-Extra: dev
Requires-Dist: autora-core[dev] ; extra == 'dev'
